{
  "last_scan": "17:04",
  "price_snapshots": {
    "2039647_yes": [
      {
        "t": 1780254218,
        "p": 0.31
      }
    ],
    "2039647_no": [
      {
        "t": 1780254218,
        "p": 0.69
      }
    ],
    "2165178_yes": [
      {
        "t": 1780270913,
        "p": 0.455
      }
    ],
    "2165178_no": [
      {
        "t": 1780270913,
        "p": 0.545
      }
    ],
    "2168275_yes": [
      {
        "t": 1780254218,
        "p": 0.28
      },
      {
        "t": 1780258758,
        "p": 0.28
      },
      {
        "t": 1780262929,
        "p": 0.275
      },
      {
        "t": 1780266893,
        "p": 0.275
      },
      {
        "t": 1780270913,
        "p": 0.26
      }
    ],
    "2168275_no": [
      {
        "t": 1780254218,
        "p": 0.72
      },
      {
        "t": 1780258758,
        "p": 0.72
      },
      {
        "t": 1780262929,
        "p": 0.725
      },
      {
        "t": 1780266893,
        "p": 0.725
      },
      {
        "t": 1780270913,
        "p": 0.74
      }
    ],
    "2158984_yes": [
      {
        "t": 1780254218,
        "p": 0.505
      }
    ],
    "2158984_no": [
      {
        "t": 1780254218,
        "p": 0.495
      }
    ],
    "2181633_yes": [
      {
        "t": 1780254218,
        "p": 0.38
      },
      {
        "t": 1780258758,
        "p": 0.375
      }
    ],
    "2181633_no": [
      {
        "t": 1780254218,
        "p": 0.62
      },
      {
        "t": 1780258758,
        "p": 0.625
      }
    ],
    "2149939_yes": [
      {
        "t": 1780254218,
        "p": 0.235
      }
    ],
    "2149939_no": [
      {
        "t": 1780254218,
        "p": 0.765
      }
    ],
    "2399832_yes": [
      {
        "t": 1780258758,
        "p": 0.305
      }
    ],
    "2399832_no": [
      {
        "t": 1780258758,
        "p": 0.695
      }
    ],
    "2404634_yes": [
      {
        "t": 1780258758,
        "p": 0.55
      }
    ],
    "2404634_no": [
      {
        "t": 1780258758,
        "p": 0.45
      }
    ],
    "2404597_yes": [
      {
        "t": 1780258758,
        "p": 0.44
      }
    ],
    "2404597_no": [
      {
        "t": 1780258758,
        "p": 0.56
      }
    ],
    "2404510_yes": [
      {
        "t": 1780258758,
        "p": 0.255
      }
    ],
    "2404510_no": [
      {
        "t": 1780258758,
        "p": 0.745
      }
    ],
    "2404498_yes": [
      {
        "t": 1780258758,
        "p": 0.67
      }
    ],
    "2404498_no": [
      {
        "t": 1780258758,
        "p": 0.33
      }
    ],
    "2404405_yes": [
      {
        "t": 1780258758,
        "p": 0.605
      }
    ],
    "2404405_no": [
      {
        "t": 1780258758,
        "p": 0.395
      }
    ],
    "2403860_yes": [
      {
        "t": 1780262929,
        "p": 0.505
      },
      {
        "t": 1780266893,
        "p": 0.505
      },
      {
        "t": 1780270913,
        "p": 0.505
      }
    ],
    "2403860_no": [
      {
        "t": 1780262929,
        "p": 0.495
      },
      {
        "t": 1780266893,
        "p": 0.495
      },
      {
        "t": 1780270913,
        "p": 0.495
      }
    ],
    "2405198_yes": [
      {
        "t": 1780266893,
        "p": 0.445
      }
    ],
    "2405198_no": [
      {
        "t": 1780266893,
        "p": 0.555
      }
    ],
    "2405185_yes": [
      {
        "t": 1780266893,
        "p": 0.605
      }
    ],
    "2405185_no": [
      {
        "t": 1780266893,
        "p": 0.395
      }
    ],
    "2399642_yes": [
      {
        "t": 1780270912,
        "p": 0.27
      }
    ],
    "2399642_no": [
      {
        "t": 1780270912,
        "p": 0.73
      }
    ],
    "2165495_yes": [
      {
        "t": 1780270913,
        "p": 0.34
      }
    ],
    "2165495_no": [
      {
        "t": 1780270913,
        "p": 0.66
      }
    ],
    "2400062_yes": [
      {
        "t": 1780270913,
        "p": 0.29
      }
    ],
    "2400062_no": [
      {
        "t": 1780270913,
        "p": 0.71
      }
    ],
    "2159022_yes": [
      {
        "t": 1780270913,
        "p": 0.26
      }
    ],
    "2159022_no": [
      {
        "t": 1780270913,
        "p": 0.74
      }
    ],
    "2405658_yes": [
      {
        "t": 1780270913,
        "p": 0.4
      }
    ],
    "2405658_no": [
      {
        "t": 1780270913,
        "p": 0.6
      }
    ],
    "2405659_yes": [
      {
        "t": 1780270913,
        "p": 0.33
      }
    ],
    "2405659_no": [
      {
        "t": 1780270913,
        "p": 0.67
      }
    ],
    "2405638_yes": [
      {
        "t": 1780270913,
        "p": 0.22
      }
    ],
    "2405638_no": [
      {
        "t": 1780270913,
        "p": 0.78
      }
    ],
    "2405656_yes": [
      {
        "t": 1780270913,
        "p": 0.7
      }
    ],
    "2405656_no": [
      {
        "t": 1780270913,
        "p": 0.3
      }
    ],
    "2391262_yes": [
      {
        "t": 1780279378,
        "p": 0.245
      }
    ],
    "2391262_no": [
      {
        "t": 1780279378,
        "p": 0.755
      }
    ],
    "2400086_yes": [
      {
        "t": 1780279378,
        "p": 0.22
      }
    ],
    "2400086_no": [
      {
        "t": 1780279378,
        "p": 0.78
      }
    ],
    "2295323_yes": [
      {
        "t": 1780279378,
        "p": 0.375
      }
    ],
    "2295323_no": [
      {
        "t": 1780279378,
        "p": 0.625
      }
    ],
    "2399940_yes": [
      {
        "t": 1780279378,
        "p": 0.305
      }
    ],
    "2399940_no": [
      {
        "t": 1780279378,
        "p": 0.695
      }
    ],
    "2394437_yes": [
      {
        "t": 1780279378,
        "p": 0.2
      }
    ],
    "2394437_no": [
      {
        "t": 1780279378,
        "p": 0.8
      }
    ],
    "2275602_yes": [
      {
        "t": 1780279378,
        "p": 0.555
      }
    ],
    "2275602_no": [
      {
        "t": 1780279378,
        "p": 0.445
      }
    ],
    "2399998_yes": [
      {
        "t": 1780279378,
        "p": 0.27
      }
    ],
    "2399998_no": [
      {
        "t": 1780279378,
        "p": 0.73
      }
    ],
    "2275608_yes": [
      {
        "t": 1780298312,
        "p": 0.565
      }
    ],
    "2275608_no": [
      {
        "t": 1780298312,
        "p": 0.435
      }
    ],
    "2391164_yes": [
      {
        "t": 1780298312,
        "p": 0.295
      }
    ],
    "2391164_no": [
      {
        "t": 1780298312,
        "p": 0.705
      }
    ],
    "2211686_yes": [
      {
        "t": 1780298312,
        "p": 0.42
      }
    ],
    "2211686_no": [
      {
        "t": 1780298312,
        "p": 0.58
      }
    ],
    "2399821_yes": [
      {
        "t": 1780298312,
        "p": 0.465
      }
    ],
    "2399821_no": [
      {
        "t": 1780298312,
        "p": 0.535
      }
    ],
    "2407123_yes": [
      {
        "t": 1780298312,
        "p": 0.31
      }
    ],
    "2407123_no": [
      {
        "t": 1780298312,
        "p": 0.69
      }
    ],
    "2184127_yes": [
      {
        "t": 1780298312,
        "p": 0.415
      }
    ],
    "2184127_no": [
      {
        "t": 1780298312,
        "p": 0.585
      }
    ],
    "2396921_yes": [
      {
        "t": 1780319048,
        "p": 0.565
      }
    ],
    "2396921_no": [
      {
        "t": 1780319048,
        "p": 0.435
      }
    ],
    "2370558_yes": [
      {
        "t": 1780319048,
        "p": 0.445
      }
    ],
    "2370558_no": [
      {
        "t": 1780319048,
        "p": 0.555
      }
    ],
    "2404583_yes": [
      {
        "t": 1780319048,
        "p": 0.51
      }
    ],
    "2404583_no": [
      {
        "t": 1780319048,
        "p": 0.49
      }
    ],
    "2168307_yes": [
      {
        "t": 1780319048,
        "p": 0.36
      }
    ],
    "2168307_no": [
      {
        "t": 1780319048,
        "p": 0.64
      }
    ],
    "2211389_yes": [
      {
        "t": 1780319049,
        "p": 0.33
      }
    ],
    "2211389_no": [
      {
        "t": 1780319049,
        "p": 0.67
      }
    ],
    "2399894_yes": [
      {
        "t": 1780319049,
        "p": 0.25
      }
    ],
    "2399894_no": [
      {
        "t": 1780319049,
        "p": 0.75
      }
    ],
    "2407229_yes": [
      {
        "t": 1780319050,
        "p": 0.21
      }
    ],
    "2407229_no": [
      {
        "t": 1780319050,
        "p": 0.79
      }
    ],
    "2168302_yes": [
      {
        "t": 1780319050,
        "p": 0.795
      }
    ],
    "2168302_no": [
      {
        "t": 1780319050,
        "p": 0.205
      }
    ],
    "2405644_yes": [
      {
        "t": 1780319050,
        "p": 0.725
      }
    ],
    "2405644_no": [
      {
        "t": 1780319050,
        "p": 0.275
      }
    ],
    "2394499_yes": [
      {
        "t": 1780319050,
        "p": 0.505
      }
    ],
    "2394499_no": [
      {
        "t": 1780319050,
        "p": 0.495
      }
    ],
    "2407173_yes": [
      {
        "t": 1780319050,
        "p": 0.315
      }
    ],
    "2407173_no": [
      {
        "t": 1780319050,
        "p": 0.685
      }
    ],
    "2409814_yes": [
      {
        "t": 1780319050,
        "p": 0.755
      }
    ],
    "2409814_no": [
      {
        "t": 1780319050,
        "p": 0.245
      }
    ],
    "2371588_yes": [
      {
        "t": 1780339646,
        "p": 0.625
      }
    ],
    "2371588_no": [
      {
        "t": 1780339646,
        "p": 0.375
      }
    ],
    "2172143_yes": [
      {
        "t": 1780339646,
        "p": 0.665
      }
    ],
    "2172143_no": [
      {
        "t": 1780339646,
        "p": 0.335
      }
    ],
    "2406643_yes": [
      {
        "t": 1780339647,
        "p": 0.44
      }
    ],
    "2406643_no": [
      {
        "t": 1780339647,
        "p": 0.56
      }
    ],
    "2407376_yes": [
      {
        "t": 1780339647,
        "p": 0.255
      }
    ],
    "2407376_no": [
      {
        "t": 1780339647,
        "p": 0.745
      }
    ],
    "2216907_yes": [
      {
        "t": 1780339647,
        "p": 0.42
      }
    ],
    "2216907_no": [
      {
        "t": 1780339647,
        "p": 0.58
      }
    ],
    "2216904_yes": [
      {
        "t": 1780339647,
        "p": 0.225
      }
    ],
    "2216904_no": [
      {
        "t": 1780339647,
        "p": 0.775
      }
    ],
    "2410113_yes": [
      {
        "t": 1780339647,
        "p": 0.485
      }
    ],
    "2410113_no": [
      {
        "t": 1780339647,
        "p": 0.515
      }
    ],
    "2184051_yes": [
      {
        "t": 1780339647,
        "p": 0.445
      }
    ],
    "2184051_no": [
      {
        "t": 1780339647,
        "p": 0.555
      }
    ],
    "2412696_yes": [
      {
        "t": 1780339648,
        "p": 0.495
      }
    ],
    "2412696_no": [
      {
        "t": 1780339648,
        "p": 0.505
      }
    ]
  },
  "category_stats": {},
  "last_telegram_update_id": 738978575,
  "cached_odds": {
    "san antonio spurs vs new york knicks": {
      "home": "San Antonio Spurs",
      "away": "New York Knicks",
      "home_prob": 0.6365,
      "away_prob": 0.3635,
      "draw_prob": 0,
      "commence": "2026-06-04T00:40:00Z",
      "sport": "basketball_nba",
      "bookmaker_count": 24
    },
    "carolina hurricanes vs vegas golden knights": {
      "home": "Carolina Hurricanes",
      "away": "Vegas Golden Knights",
      "home_prob": 0.4618,
      "away_prob": 0.3279,
      "draw_prob": 0.2103,
      "commence": "2026-06-03T00:20:09Z",
      "sport": "icehockey_nhl",
      "bookmaker_count": 21
    },
    "tampa bay rays vs detroit tigers": {
      "home": "Tampa Bay Rays",
      "away": "Detroit Tigers",
      "home_prob": 0.555,
      "away_prob": 0.445,
      "draw_prob": 0,
      "commence": "2026-06-02T22:41:00Z",
      "sport": "baseball_mlb",
      "bookmaker_count": 8
    },
    "washington nationals vs miami marlins": {
      "home": "Washington Nationals",
      "away": "Miami Marlins",
      "home_prob": 0.5655,
      "away_prob": 0.4345,
      "draw_prob": 0,
      "commence": "2026-06-01T22:46:00Z",
      "sport": "baseball_mlb",
      "bookmaker_count": 22
    },
    "cincinnati reds vs kansas royals": {
      "home": "Cincinnati Reds",
      "away": "Kansas City Royals",
      "home_prob": 0.5367,
      "away_prob": 0.4633,
      "draw_prob": 0,
      "commence": "2026-06-02T23:11:00Z",
      "sport": "baseball_mlb",
      "bookmaker_count": 8
    },
    "minnesota twins vs chicago white sox": {
      "home": "Minnesota Twins",
      "away": "Chicago White Sox",
      "home_prob": 0.4936,
      "away_prob": 0.5064,
      "draw_prob": 0,
      "commence": "2026-06-02T23:41:00Z",
      "sport": "baseball_mlb",
      "bookmaker_count": 1
    },
    "milwaukee brewers vs san francisco giants": {
      "home": "Milwaukee Brewers",
      "away": "San Francisco Giants",
      "home_prob": 0.5739,
      "away_prob": 0.4261,
      "draw_prob": 0,
      "commence": "2026-06-01T23:41:00Z",
      "sport": "baseball_mlb",
      "bookmaker_count": 22
    },
    "st louisrdinals vs texas rangers": {
      "home": "St. Louis Cardinals",
      "away": "Texas Rangers",
      "home_prob": 0.4717,
      "away_prob": 0.5283,
      "draw_prob": 0,
      "commence": "2026-06-01T23:46:00Z",
      "sport": "baseball_mlb",
      "bookmaker_count": 22
    },
    "los angeles angels vs colorado rockies": {
      "home": "Los Angeles Angels",
      "away": "Colorado Rockies",
      "home_prob": 0.6418,
      "away_prob": 0.3582,
      "draw_prob": 0,
      "commence": "2026-06-02T01:39:00Z",
      "sport": "baseball_mlb",
      "bookmaker_count": 22
    },
    "arizona diamondbacks vs los angeles dodgers": {
      "home": "Arizona Diamondbacks",
      "away": "Los Angeles Dodgers",
      "home_prob": 0.4062,
      "away_prob": 0.5938,
      "draw_prob": 0,
      "commence": "2026-06-02T01:41:00Z",
      "sport": "baseball_mlb",
      "bookmaker_count": 21
    },
    "seattle mariners vs new york mets": {
      "home": "Seattle Mariners",
      "away": "New York Mets",
      "home_prob": 0.5441,
      "away_prob": 0.4559,
      "draw_prob": 0,
      "commence": "2026-06-02T01:41:00Z",
      "sport": "baseball_mlb",
      "bookmaker_count": 21
    },
    "philadelphia phillies vs san diego padres": {
      "home": "Philadelphia Phillies",
      "away": "San Diego Padres",
      "home_prob": 0.5425,
      "away_prob": 0.4575,
      "draw_prob": 0,
      "commence": "2026-06-02T22:41:00Z",
      "sport": "baseball_mlb",
      "bookmaker_count": 8
    },
    "boston red sox vs baltimore orioles": {
      "home": "Boston Red Sox",
      "away": "Baltimore Orioles",
      "home_prob": 0.5456,
      "away_prob": 0.4544,
      "draw_prob": 0,
      "commence": "2026-06-02T22:46:00Z",
      "sport": "baseball_mlb",
      "bookmaker_count": 8
    },
    "new york yankees vs cleveland guardians": {
      "home": "New York Yankees",
      "away": "Cleveland Guardians",
      "home_prob": 0.648,
      "away_prob": 0.352,
      "draw_prob": 0,
      "commence": "2026-06-02T23:06:00Z",
      "sport": "baseball_mlb",
      "bookmaker_count": 8
    },
    "atlanta braves vs toronto blue jays": {
      "home": "Atlanta Braves",
      "away": "Toronto Blue Jays",
      "home_prob": 0.5386,
      "away_prob": 0.4614,
      "draw_prob": 0,
      "commence": "2026-06-02T23:16:00Z",
      "sport": "baseball_mlb",
      "bookmaker_count": 3
    },
    "islam makhachev vs ilia topuria": {
      "home": "Islam Makhachev",
      "away": "Ilia Topuria",
      "home_prob": 0.6765,
      "away_prob": 0.3235,
      "draw_prob": 0,
      "commence": "2026-06-02T02:00:00Z",
      "sport": "mma_mixed_martial_arts",
      "bookmaker_count": 1
    },
    "bryce mitchell vs santiago luna": {
      "home": "Bryce Mitchell",
      "away": "Santiago Luna",
      "home_prob": 0.5544,
      "away_prob": 0.4273,
      "draw_prob": 0.0183,
      "commence": "2026-06-06T09:00:00Z",
      "sport": "mma_mixed_martial_arts",
      "bookmaker_count": 11
    },
    "ketlen souza vs arianernelossi": {
      "home": "Ketlen Souza",
      "away": "Ariane Carnelossi",
      "home_prob": 0.6687,
      "away_prob": 0.3062,
      "draw_prob": 0.0251,
      "commence": "2026-06-06T21:00:00Z",
      "sport": "mma_mixed_martial_arts",
      "bookmaker_count": 9
    },
    "belal muhammad vs gabriel bonfim": {
      "home": "Belal Muhammad",
      "away": "Gabriel Bonfim",
      "home_prob": 0.539,
      "away_prob": 0.4428,
      "draw_prob": 0.0182,
      "commence": "2026-06-06T21:00:00Z",
      "sport": "mma_mixed_martial_arts",
      "bookmaker_count": 13
    },
    "brendan allen vs edmen shahbazyan": {
      "home": "Brendan Allen",
      "away": "Edmen Shahbazyan",
      "home_prob": 0.6534,
      "away_prob": 0.3283,
      "draw_prob": 0.0183,
      "commence": "2026-06-06T21:00:00Z",
      "sport": "mma_mixed_martial_arts",
      "bookmaker_count": 13
    },
    "bruno silva vs edgar chairez": {
      "home": "Bruno Silva",
      "away": "Edgar Chairez",
      "home_prob": 0.5287,
      "away_prob": 0.454,
      "draw_prob": 0.0173,
      "commence": "2026-06-06T21:00:00Z",
      "sport": "mma_mixed_martial_arts",
      "bookmaker_count": 6
    },
    "priscilachoeira vs chelsea chandler": {
      "home": "Priscila Cachoeira",
      "away": "Chelsea Chandler",
      "home_prob": 0.4818,
      "away_prob": 0.5002,
      "draw_prob": 0.018,
      "commence": "2026-06-06T21:00:00Z",
      "sport": "mma_mixed_martial_arts",
      "bookmaker_count": 8
    },
    "fares ziam vs tom nolan": {
      "home": "Fares Ziam",
      "away": "Tom Nolan",
      "home_prob": 0.7129,
      "away_prob": 0.2687,
      "draw_prob": 0.0183,
      "commence": "2026-06-06T21:00:00Z",
      "sport": "mma_mixed_martial_arts",
      "bookmaker_count": 12
    },
    "iwo baraniewski vs junior tafa": {
      "home": "Iwo Baraniewski",
      "away": "Junior Tafa",
      "home_prob": 0.7053,
      "away_prob": 0.2762,
      "draw_prob": 0.0185,
      "commence": "2026-06-06T21:00:00Z",
      "sport": "mma_mixed_martial_arts",
      "bookmaker_count": 12
    },
    "jeisla chaves vs yuneisy duben": {
      "home": "Jeisla Chaves",
      "away": "Yuneisy Duben",
      "home_prob": 0.7339,
      "away_prob": 0.2483,
      "draw_prob": 0.0178,
      "commence": "2026-06-06T21:00:00Z",
      "sport": "mma_mixed_martial_arts",
      "bookmaker_count": 8
    },
    "jordan leavitt vs joanderson brito": {
      "home": "Jordan Leavitt",
      "away": "Joanderson Brito",
      "home_prob": 0.3836,
      "away_prob": 0.5986,
      "draw_prob": 0.0178,
      "commence": "2026-06-06T21:00:00Z",
      "sport": "mma_mixed_martial_arts",
      "bookmaker_count": 9
    },
    "marcus mcghee vs john yannis": {
      "home": "Marcus McGhee",
      "away": "John Yannis",
      "home_prob": 0.784,
      "away_prob": 0.1974,
      "draw_prob": 0.0186,
      "commence": "2026-06-06T21:00:00Z",
      "sport": "mma_mixed_martial_arts",
      "bookmaker_count": 9
    },
    "matthnell vs alessandro costa": {
      "home": "Matt Schnell",
      "away": "Alessandro Costa",
      "home_prob": 0.1686,
      "away_prob": 0.8131,
      "draw_prob": 0.0183,
      "commence": "2026-06-06T22:00:00Z",
      "sport": "mma_mixed_martial_arts",
      "bookmaker_count": 8
    },
    "alex pereira vs carlos ulberg": {
      "home": "Alex Pereira",
      "away": "Carlos Ulberg",
      "home_prob": 0.6143,
      "away_prob": 0.3857,
      "draw_prob": 0,
      "commence": "2026-06-14T02:00:00Z",
      "sport": "mma_mixed_martial_arts",
      "bookmaker_count": 1
    },
    "alex pereira vs jiri prochazka": {
      "home": "Alex Pereira",
      "away": "Jiri Prochazka",
      "home_prob": 0.7246,
      "away_prob": 0.2754,
      "draw_prob": 0,
      "commence": "2026-06-14T02:00:00Z",
      "sport": "mma_mixed_martial_arts",
      "bookmaker_count": 1
    },
    "alex pereira vs jon jones": {
      "home": "Alex Pereira",
      "away": "Jon Jones",
      "home_prob": 0.3111,
      "away_prob": 0.6889,
      "draw_prob": 0,
      "commence": "2026-06-14T02:00:00Z",
      "sport": "mma_mixed_martial_arts",
      "bookmaker_count": 1
    },
    "magomed ankalaev vs carlos ulberg": {
      "home": "Magomed Ankalaev",
      "away": "Carlos Ulberg",
      "home_prob": 0.6889,
      "away_prob": 0.3111,
      "draw_prob": 0,
      "commence": "2026-06-14T02:00:00Z",
      "sport": "mma_mixed_martial_arts",
      "bookmaker_count": 1
    },
    "diego lopes vs steve garcia jr": {
      "home": "Diego Lopes",
      "away": "Steve Garcia Jr.",
      "home_prob": 0.5994,
      "away_prob": 0.3726,
      "draw_prob": 0.0279,
      "commence": "2026-06-14T22:10:00Z",
      "sport": "mma_mixed_martial_arts",
      "bookmaker_count": 13
    },
    "bo nickal vs kyle daukaus": {
      "home": "Bo Nickal",
      "away": "Kyle Daukaus",
      "home_prob": 0.7073,
      "away_prob": 0.2647,
      "draw_prob": 0.028,
      "commence": "2026-06-14T22:30:00Z",
      "sport": "mma_mixed_martial_arts",
      "bookmaker_count": 12
    },
    "derrick lewis vs josh hokit": {
      "home": "Derrick Lewis",
      "away": "Josh Hokit",
      "home_prob": 0.2557,
      "away_prob": 0.7164,
      "draw_prob": 0.0279,
      "commence": "2026-06-14T22:50:00Z",
      "sport": "mma_mixed_martial_arts",
      "bookmaker_count": 11
    },
    "mauricio ruffy vs michael chandler": {
      "home": "Mauricio Ruffy",
      "away": "Michael Chandler",
      "home_prob": 0.7987,
      "away_prob": 0.1733,
      "draw_prob": 0.028,
      "commence": "2026-06-14T23:15:00Z",
      "sport": "mma_mixed_martial_arts",
      "bookmaker_count": 12
    },
    "sean omalley vs aiemann zahabi": {
      "home": "Sean O'Malley",
      "away": "Aiemann Zahabi",
      "home_prob": 0.7439,
      "away_prob": 0.228,
      "draw_prob": 0.028,
      "commence": "2026-06-14T23:45:00Z",
      "sport": "mma_mixed_martial_arts",
      "bookmaker_count": 13
    },
    "alex pereira vs ciryl gane": {
      "home": "Alex Pereira",
      "away": "Ciryl Gane",
      "home_prob": 0.4934,
      "away_prob": 0.488,
      "draw_prob": 0.0186,
      "commence": "2026-06-15T00:30:00Z",
      "sport": "mma_mixed_martial_arts",
      "bookmaker_count": 13
    },
    "ilia topuria vs justin gaethje": {
      "home": "Ilia Topuria",
      "away": "Justin Gaethje",
      "home_prob": 0.8181,
      "away_prob": 0.1632,
      "draw_prob": 0.0188,
      "commence": "2026-06-15T01:15:00Z",
      "sport": "mma_mixed_martial_arts",
      "bookmaker_count": 14
    },
    "valentina shevchenko vs natalia silva": {
      "home": "Valentina Shevchenko",
      "away": "Natalia Silva",
      "home_prob": 0.6889,
      "away_prob": 0.3111,
      "draw_prob": 0,
      "commence": "2026-06-27T14:00:00Z",
      "sport": "mma_mixed_martial_arts",
      "bookmaker_count": 1
    },
    "alexandre pantoja vs joshua van": {
      "home": "Alexandre Pantoja",
      "away": "Joshua Van",
      "home_prob": 0.6143,
      "away_prob": 0.3857,
      "draw_prob": 0,
      "commence": "2026-06-28T02:00:00Z",
      "sport": "mma_mixed_martial_arts",
      "bookmaker_count": 1
    },
    "tom aspinall vs ciryl gane": {
      "home": "Tom Aspinall",
      "away": "Ciryl Gane",
      "home_prob": 0.5722,
      "away_prob": 0.3993,
      "draw_prob": 0.0284,
      "commence": "2026-12-31T20:00:00Z",
      "sport": "mma_mixed_martial_arts",
      "bookmaker_count": 1
    },
    "islam makhachev vs michael morales": {
      "home": "Islam Makhachev",
      "away": "Michael Morales",
      "home_prob": 0.7426,
      "away_prob": 0.2574,
      "draw_prob": 0,
      "commence": "2026-06-28T02:00:00Z",
      "sport": "mma_mixed_martial_arts",
      "bookmaker_count": 1
    },
    "weili zhang vs mackenzie dern": {
      "home": "Weili Zhang",
      "away": "Mackenzie Dern",
      "home_prob": 0.7867,
      "away_prob": 0.2133,
      "draw_prob": 0,
      "commence": "2026-06-28T02:00:00Z",
      "sport": "mma_mixed_martial_arts",
      "bookmaker_count": 1
    },
    "merab dvalishvili vs petr yan": {
      "home": "Merab Dvalishvili",
      "away": "Petr Yan",
      "home_prob": 0.3857,
      "away_prob": 0.6143,
      "draw_prob": 0,
      "commence": "2026-06-28T02:00:00Z",
      "sport": "mma_mixed_martial_arts",
      "bookmaker_count": 1
    },
    "brandon royval vs loneer kavanagh": {
      "home": "Brandon Royval",
      "away": "Lone'er Kavanagh",
      "home_prob": 0.3669,
      "away_prob": 0.605,
      "draw_prob": 0.0281,
      "commence": "2026-07-12T02:00:00Z",
      "sport": "mma_mixed_martial_arts",
      "bookmaker_count": 5
    },
    "cory sandhagen vs mario bautista": {
      "home": "Cory Sandhagen",
      "away": "Mario Bautista",
      "home_prob": 0.5589,
      "away_prob": 0.4132,
      "draw_prob": 0.0279,
      "commence": "2026-07-12T02:00:00Z",
      "sport": "mma_mixed_martial_arts",
      "bookmaker_count": 6
    },
    "gable steveson vs elisha ellison": {
      "home": "Gable Steveson",
      "away": "Elisha Ellison",
      "home_prob": 0.8933,
      "away_prob": 0.0793,
      "draw_prob": 0.0274,
      "commence": "2026-07-12T02:00:00Z",
      "sport": "mma_mixed_martial_arts",
      "bookmaker_count": 5
    },
    "paddy pimblett vs benoit saintdenis": {
      "home": "Paddy Pimblett",
      "away": "Benoit Saint-Denis",
      "home_prob": 0.3793,
      "away_prob": 0.5928,
      "draw_prob": 0.0279,
      "commence": "2026-07-12T02:45:00Z",
      "sport": "mma_mixed_martial_arts",
      "bookmaker_count": 7
    },
    "conor mcgregor vs max holloway": {
      "home": "Conor McGregor",
      "away": "Max Holloway",
      "home_prob": 0.2555,
      "away_prob": 0.7164,
      "draw_prob": 0.0281,
      "commence": "2026-07-12T03:30:00Z",
      "sport": "mma_mixed_martial_arts",
      "bookmaker_count": 13
    },
    "dricus du plessis vs kamaru usman": {
      "home": "Dricus Du Plessis",
      "away": "Kamaru Usman",
      "home_prob": 0.749,
      "away_prob": 0.251,
      "draw_prob": 0,
      "commence": "2026-07-18T22:00:00Z",
      "sport": "mma_mixed_martial_arts",
      "bookmaker_count": 1
    },
    "ilia topuria vs arman tsarukyan": {
      "home": "Ilia Topuria",
      "away": "Arman Tsarukyan",
      "home_prob": 0.634,
      "away_prob": 0.366,
      "draw_prob": 0,
      "commence": "2026-08-02T03:10:00Z",
      "sport": "mma_mixed_martial_arts",
      "bookmaker_count": 1
    },
    "manel kape vs joshua van": {
      "home": "Manel Kape",
      "away": "Joshua Van",
      "home_prob": 0.5875,
      "away_prob": 0.4125,
      "draw_prob": 0,
      "commence": "2026-12-27T03:00:00Z",
      "sport": "mma_mixed_martial_arts",
      "bookmaker_count": 1
    },
    "conor mcgregor vs jorge masvidal": {
      "home": "Conor McGregor",
      "away": "Jorge Masvidal",
      "home_prob": 0.5711,
      "away_prob": 0.4289,
      "draw_prob": 0,
      "commence": "2026-12-31T17:00:00Z",
      "sport": "mma_mixed_martial_arts",
      "bookmaker_count": 1
    },
    "islam makhachev vs kamaru usman": {
      "home": "Islam Makhachev",
      "away": "Kamaru Usman",
      "home_prob": 0.74,
      "away_prob": 0.26,
      "draw_prob": 0,
      "commence": "2027-07-02T02:00:00Z",
      "sport": "mma_mixed_martial_arts",
      "bookmaker_count": 1
    },
    "khamzat chimaev vs paulo henrique costa": {
      "home": "Khamzat Chimaev",
      "away": "Paulo Henrique Costa",
      "home_prob": 0.7983,
      "away_prob": 0.2017,
      "draw_prob": 0,
      "commence": "2027-01-01T03:00:00Z",
      "sport": "mma_mixed_martial_arts",
      "bookmaker_count": 1
    },
    "sean strickland vs khamzat chimaev": {
      "home": "Sean Strickland",
      "away": "Khamzat Chimaev",
      "home_prob": 0.3514,
      "away_prob": 0.6486,
      "draw_prob": 0,
      "commence": "2027-01-01T03:00:00Z",
      "sport": "mma_mixed_martial_arts",
      "bookmaker_count": 1
    },
    "sean strickland vs nassourdine imavov": {
      "home": "Sean Strickland",
      "away": "Nassourdine Imavov",
      "home_prob": 0.4921,
      "away_prob": 0.5079,
      "draw_prob": 0,
      "commence": "2027-01-01T03:00:00Z",
      "sport": "mma_mixed_martial_arts",
      "bookmaker_count": 1
    }
  },
  "odds_last_fetched": 1780339640
}